<?xml version="1.0" encoding="UTF-8"?>
<buildprofiles xmlns:xsi="http://www.w3.org/2001/XMLSchema-instance"
               xsi:noNamespaceSchemaLocation="https://resources.jetbrains.com/writerside/1.0/build-profiles.xsd">

    <variables>
        <primary-color>emerald</primary-color>
        <color-preset>vivid</color-preset>
        <web-root>https://suresh.dev/</web-root>
        <header-logo>header-logo.png</header-logo>
        <product-web-url>https://suresh.dev/</product-web-url>
        <search-scope/>
        <download-title>suresh.dev</download-title>
        <download-page>https://suresh.dev</download-page>
        <showDownloadButton>true</showDownloadButton>
        <og-twitter>@sur3shg</og-twitter>
        <algolia-id>QD1IR5ST5F</algolia-id>
        <algolia-index>suresh.dev.index</algolia-index>
        <algolia-api-key>e205ec1712a2f745af4bdb1224d7f3e9</algolia-api-key>
    </variables>

    <footer>
        <copyright>Suresh 2024</copyright>
        <social type="blog" href="https://suresh.dev/notes"/>
        <social type="twitter" href="https://twitter.com/sur3shg"/>
        <link href="https://github.com/sureshg">Github</link>
    </footer>

    <build-profile instance="blog">
        <variables>
            <noindex-content>false</noindex-content>
            <offline-docs>true</offline-docs>
        </variables>
    </build-profile>

    <build-profile instance="notes">
        <variables>
            <noindex-content>false</noindex-content>
            <offline-docs>true</offline-docs>
        </variables>
    </build-profile>
</buildprofiles>
